{
  "fe/sg15/z=16/nc/v1.2": {
    "convergence_phonon_frequencies": {
      "output_parameters": {
        "ecutrho": [
          120.0,
          140.0,
          160.0,
          180.0,
          200.0,
          220.0,
          240.0,
          260.0,
          280.0,
          300.0,
          320.0,
          360.0,
          400.0,
          480.0,
          600.0,
          800.0
        ],
        "ecutwfc": [
          30.0,
          35.0,
          40.0,
          45.0,
          50.0,
          55.0,
          60.0,
          65.0,
          70.0,
          75.0,
          80.0,
          90.0,
          100.0,
          120.0,
          150.0,
          200.0
        ],
        "absolute_diff": [
          -378.757806,
          490.581766,
          552.07501,
          -125.085674,
          -64.787945,
          38.0472,
          10.457223,
          0.685845,
          0.665279,
          0.89056399999998,
          0.51989999999998,
          0.50742299999999,
          0.21723999999998,
          0.049290999999982,
          -0.0030240000000106,
          0.0
        ],
        "absolute_unit": "cm-1",
        "relative_diff": [
          199.01783844063,
          257.77560515204,
          290.08715703483,
          65.726118551256,
          34.042748602548,
          19.991855963804,
          5.494735381247,
          0.36037643909395,
          0.3495700588675,
          0.46794579402818,
          0.27318083631861,
          0.26662481151625,
          0.11414849948423,
          0.025899897293665,
          0.0015889572014433,
          0.0
        ],
        "relative_unit": "%",
        "absolute_max_diff": [
          -378.757806,
          490.581766,
          552.07501,
          -125.085674,
          -64.787945,
          38.0472,
          10.457223,
          0.685845,
          0.665279,
          0.89056399999998,
          0.51989999999998,
          0.50742299999999,
          0.21723999999998,
          0.049290999999982,
          -0.0030240000000106,
          0.0
        ],
        "relative_max_diff": [
          199.01783844063,
          -257.77560515204,
          -290.08715703483,
          65.726118551256,
          34.042748602548,
          -19.991855963804,
          -5.494735381247,
          -0.36037643909395,
          -0.3495700588675,
          -0.46794579402818,
          -0.27318083631861,
          -0.26662481151625,
          -0.11414849948423,
          -0.025899897293665,
          0.0015889572014433,
          0.0
        ]
      }
    },
    "convergence_pressure": {
      "output_parameters": {
        "ecutrho": [
          120.0,
          140.0,
          160.0,
          180.0,
          200.0,
          220.0,
          240.0,
          260.0,
          280.0,
          300.0,
          320.0,
          360.0,
          400.0,
          480.0,
          600.0,
          800.0
        ],
        "ecutwfc": [
          30.0,
          35.0,
          40.0,
          45.0,
          50.0,
          55.0,
          60.0,
          65.0,
          70.0,
          75.0,
          80.0,
          90.0,
          100.0,
          120.0,
          150.0,
          200.0
        ],
        "pressure": [
          -1446.6830293029,
          -863.96651748802,
          -482.73332553999,
          -259.54892099922,
          -128.81916027881,
          -56.411993220105,
          -29.42468843007,
          -20.75858259278,
          -18.453740606417,
          -18.069796415428,
          -18.076121932751,
          -18.073179831671,
          -18.074062461995,
          -18.062441162727,
          -18.064206423375,
          -18.061411427349
        ],
        "absolute_diff": [
          1428.6216178756,
          845.90510606067,
          464.67191411264,
          241.48750957187,
          110.75774885146,
          38.350581792756,
          11.363277002721,
          2.697171165431,
          0.392329179068,
          0.0083849880790012,
          0.014710505402,
          0.011768404321998,
          0.012651034645998,
          0.0010297353780011,
          0.002794996026001,
          0.0
        ],
        "absolute_unit": "GPascal",
        "relative_diff": [
          54.434881143182,
          47.79727485505,
          39.743303808868,
          30.787564935233,
          20.798459535247,
          10.289803009341,
          3.7301969503837,
          0.96008300623589,
          0.14296636033704,
          0.0030677543666565,
          0.0053816698638131,
          0.0043054681048772,
          0.004628335572426,
          0.00037677069259083,
          0.0010226444627304,
          2.7059800495391e-13
        ],
        "relative_unit": "%"
      }
    },
    "delta_factor": {
      "output_birch_murnaghan_fit": {
        "energy0": -3220.6045996,
        "volume0": 11.448406,
        "residuals0": 0,
        "bulk_deriv0": 6.9000409,
        "volume0_unit": "A^3/atom",
        "bulk_modulus0": 180.3727025,
        "bulk_modulus0_unit": "GPa"
      },
      "output_delta_factor": {
        "delta": 4.4272992179172,
        "delta1": 6.1661969182531,
        "delta_unit": "meV/atom",
        "delta_relative": 39.764034067481,
        "delta_relative_unit": "%",
        "birch_murnaghan_results": [
          11.448406,
          180.3727025,
          6.9000409
        ],
        "reference_wien2k_V0_B0_B1": [
          11.3436,
          197.652,
          5.8
        ]
      },
      "output_volume_energy": {
        "volumes": {
          "0": 10.692323777927,
          "1": 10.919820028664,
          "2": 11.147316279711,
          "3": 11.37481252979,
          "4": 11.602308780805,
          "5": 11.829805030753,
          "6": 12.057301282059
        },
        "energies": {
          "0": -3220.5710234183,
          "1": -3220.5889551758,
          "2": -3220.5998005447,
          "3": -3220.6044294051,
          "4": -3220.6035656478,
          "5": -3220.5978346583,
          "6": -3220.5887858529
        },
        "energy_unit": "eV/atom",
        "volume_unit": "A^3/atom"
      }
    },
    "pseudo_info": {
      "element": "Fe",
      "pp_type": "NC",
      "z_valence": 16
    }
  },
  "fe/dojo/z=16/nc/v04": {
    "convergence_cohesive_energy": {
      "output_parameters": {
        "ecutrho": [
          120.0,
          140.0,
          160.0,
          180.0,
          200.0,
          220.0,
          240.0,
          260.0,
          300.0,
          320.0,
          360.0,
          400.0,
          600.0,
          800.0
        ],
        "ecutwfc": [
          30.0,
          35.0,
          40.0,
          45.0,
          50.0,
          55.0,
          60.0,
          65.0,
          75.0,
          80.0,
          90.0,
          100.0,
          150.0,
          200.0
        ],
        "absolute_diff": [
          -2.5426470440599,
          -2.8778080213259,
          -1.8203742046813,
          -0.7367982758451,
          -0.1635491222019,
          -0.3057087363855,
          -0.1440437304368,
          -0.0327762473562,
          -0.0076552425017002,
          -0.0025977347737003,
          8.1633865995911e-06,
          3.5102700100431e-05,
          -1.0206725982303,
          0.0
        ],
        "absolute_unit": "eV/atom",
        "relative_diff": [
          32.976889336537,
          37.323763387754,
          23.609363650808,
          9.5559134967861,
          2.1211521734956,
          3.9648928830091,
          1.868176776377,
          0.42509190745033,
          0.099284753427608,
          0.033691350263545,
          0.00010587513400061,
          0.00045526486239208,
          13.237624702693,
          0.0
        ],
        "relative_unit": "%",
        "cohesive_energy_per_atom": [
          -10.25303785173,
          -10.588198828996,
          -9.5307650123514,
          -8.4471890835152,
          -7.873939929872,
          -8.0160995440556,
          -7.8544345381069,
          -7.7431670550263,
          -7.7180460501718,
          -7.7129885424438,
          -7.7103826442835,
          -7.71035570497,
          -8.7310634059004,
          -7.7103908076701
        ]
      }
    },
    "convergence_phonon_frequencies": {
      "output_parameters": {
        "ecutrho": [
          120.0,
          140.0,
          160.0,
          180.0,
          200.0,
          220.0,
          240.0,
          260.0,
          280.0,
          300.0,
          320.0,
          360.0,
          400.0,
          480.0,
          600.0,
          800.0
        ],
        "ecutwfc": [
          30.0,
          35.0,
          40.0,
          45.0,
          50.0,
          55.0,
          60.0,
          65.0,
          70.0,
          75.0,
          80.0,
          90.0,
          100.0,
          120.0,
          150.0,
          200.0
        ],
        "absolute_diff": [
          -661.021389,
          501.244414,
          636.563142,
          -232.210131,
          -183.089107,
          487.427405,
          219.058074,
          -29.766599,
          -28.297216,
          -0.833089,
          1.253411,
          0.093252000000007,
          0.056021000000015,
          0.0069459999999992,
          0.057930999999996,
          0.0
        ],
        "absolute_unit": "cm-1",
        "relative_diff": [
          340.11896863356,
          257.90804346123,
          327.53433236815,
          119.48035506304,
          94.205844587095,
          250.79870187428,
          112.71315488361,
          15.315971797713,
          14.559922086154,
          0.42865386230333,
          0.6449244512933,
          0.047981464126298,
          0.028824793053445,
          0.0035739635591859,
          0.029807555851887,
          0.0
        ],
        "relative_unit": "%",
        "absolute_max_diff": [
          -661.021389,
          501.244414,
          636.563142,
          -232.210131,
          -183.089107,
          487.427405,
          219.058074,
          -29.766599,
          -28.297216,
          -0.833089,
          1.253411,
          0.093252000000007,
          0.056021000000015,
          0.0069459999999992,
          0.057930999999996,
          0.0
        ],
        "relative_max_diff": [
          340.11896863356,
          -257.90804346123,
          -327.53433236815,
          119.48035506304,
          94.205844587095,
          -250.79870187428,
          -112.71315488361,
          15.315971797713,
          14.559922086154,
          0.42865386230333,
          -0.6449244512933,
          -0.047981464126298,
          -0.028824793053445,
          -0.0035739635591859,
          -0.029807555851887,
          0.0
        ]
      }
    },
    "convergence_pressure": {
      "output_parameters": {
        "ecutrho": [
          120.0,
          140.0,
          160.0,
          180.0,
          200.0,
          220.0,
          240.0,
          260.0,
          280.0,
          300.0,
          320.0,
          360.0,
          400.0,
          480.0,
          600.0,
          800.0
        ],
        "ecutwfc": [
          30.0,
          35.0,
          40.0,
          45.0,
          50.0,
          55.0,
          60.0,
          65.0,
          70.0,
          75.0,
          80.0,
          90.0,
          100.0,
          120.0,
          150.0,
          200.0
        ],
        "pressure": [
          -2456.5909998323,
          -1866.4203807201,
          -1360.0515390459,
          -958.0747692206,
          -633.39081950808,
          -375.9590344463,
          -213.51004066324,
          -117.08414880459,
          -62.467866978888,
          -34.331965927076,
          -23.200085174327,
          -18.71632312784,
          -18.614820640567,
          -18.607759597974,
          -18.608789333352,
          -18.607171177758
        ],
        "absolute_diff": [
          2437.9838286545,
          1847.8132095423,
          1341.4443678681,
          939.46759804284,
          614.78364833032,
          357.35186326854,
          194.90286948548,
          98.476977626832,
          43.86069580113,
          15.724794749318,
          4.592913996569,
          0.109151950082,
          0.0076494628089989,
          0.00058842021599759,
          0.0016181555939987,
          0.0
        ],
        "absolute_unit": "GPascal",
        "relative_diff": [
          60.617600154265,
          57.47164166684,
          53.635833106146,
          49.141258712733,
          43.537026044727,
          36.135002749084,
          27.929349966693,
          19.440601276679,
          11.383826584413,
          4.983973887081,
          1.6086780864597,
          0.040000241460791,
          0.002806235617152,
          0.00021588027097607,
          0.00059366433120861,
          6.7867909822479e-14
        ],
        "relative_unit": "%"
      }
    },
    "delta_factor": {
      "output_birch_murnaghan_fit": {
        "energy0": -3410.6528314,
        "volume0": 11.4349476,
        "residuals0": 0,
        "bulk_deriv0": 9.9658017,
        "volume0_unit": "A^3/atom",
        "bulk_modulus0": 167.3547388,
        "bulk_modulus0_unit": "GPa"
      },
      "output_delta_factor": {
        "delta": 4.2477769356582,
        "delta1": 6.1307843025242,
        "delta_unit": "meV/atom",
        "delta_relative": 39.24449525891,
        "delta_relative_unit": "%",
        "birch_murnaghan_results": [
          11.4349476,
          167.3547388,
          9.9658017
        ],
        "reference_wien2k_V0_B0_B1": [
          11.3436,
          197.652,
          5.8
        ]
      },
      "output_volume_energy": {
        "volumes": {
          "0": 10.692323777927,
          "1": 10.919820028664,
          "2": 11.147316279711,
          "3": 11.37481252979,
          "4": 11.602308780805,
          "5": 11.829805030753,
          "6": 12.057301282059
        },
        "energies": {
          "0": -3410.620937513,
          "1": -3410.6382655178,
          "2": -3410.6486558445,
          "3": -3410.6529452429,
          "4": -3410.6518174671,
          "5": -3410.6460357284,
          "6": -3410.6385258628
        },
        "energy_unit": "eV/atom",
        "volume_unit": "A^3/atom"
      }
    },
    "pseudo_info": {
      "element": "Fe",
      "pp_type": "NC",
      "z_valence": 16
    }
  },
  "fe/psl(low)/z=8/us/v1.0.0": {
    "convergence_cohesive_energy": {
      "output_parameters": {
        "ecutrho": [
          240.0,
          400.0,
          440.0,
          480.0,
          520.0,
          600.0,
          640.0,
          720.0,
          960.0,
          1200.0,
          1600.0
        ],
        "ecutwfc": [
          30.0,
          50.0,
          55.0,
          60.0,
          65.0,
          75.0,
          80.0,
          90.0,
          120.0,
          150.0,
          200.0
        ],
        "absolute_diff": [
          -0.0032573386532997,
          -0.00029320265880006,
          -0.00048517895589928,
          -0.00014109101719928,
          -0.00021891558289955,
          -0.00024653513529937,
          -0.00018394895290008,
          -5.8776582299913e-05,
          -1.3333577599361e-05,
          -1.7551336899402e-05,
          0.0
        ],
        "absolute_unit": "eV/atom",
        "relative_diff": [
          0.042115278671413,
          0.0037909204405428,
          0.0062730495990966,
          0.0018242154531158,
          0.0028304366725854,
          0.0031875395930693,
          0.0023783407982016,
          0.00075994313345544,
          0.00017239452081999,
          0.00022692741628979,
          0.0
        ],
        "relative_unit": "%",
        "cohesive_energy_per_atom": [
          -7.7375968849109,
          -7.7346327489164,
          -7.7348247252135,
          -7.7344806372748,
          -7.7345584618405,
          -7.7345860813929,
          -7.7345234952105,
          -7.7343983228399,
          -7.7343528798352,
          -7.7343570975945,
          -7.7343395462576
        ]
      }
    },
    "convergence_phonon_frequencies": {
      "output_parameters": {
        "ecutrho": [
          240.0,
          280.0,
          320.0,
          360.0,
          400.0,
          440.0,
          480.0,
          520.0,
          560.0,
          600.0,
          640.0,
          720.0,
          800.0,
          960.0,
          1200.0,
          1600.0
        ],
        "ecutwfc": [
          30.0,
          35.0,
          40.0,
          45.0,
          50.0,
          55.0,
          60.0,
          65.0,
          70.0,
          75.0,
          80.0,
          90.0,
          100.0,
          120.0,
          150.0,
          200.0
        ],
        "absolute_diff": [
          -3.122092,
          2.159639,
          -0.37410799999999,
          -4.329858,
          -1.728906,
          -0.013072999999991,
          -0.19721699999999,
          -0.13274799999999,
          -0.062141999999994,
          0.452505,
          0.365329,
          0.13136300000001,
          0.200793,
          0.064546000000007,
          0.012014000000008,
          0.0
        ],
        "absolute_unit": "cm-1",
        "relative_diff": [
          2.7023997987992,
          1.8693260797821,
          0.3238179348748,
          3.7478099261742,
          1.4964950509283,
          0.011315641105284,
          0.17070578993821,
          0.11490313818138,
          0.053788462446643,
          0.39167629299701,
          0.31621906596459,
          0.1137043190174,
          0.1738010804295,
          0.055869300908914,
          0.010398998870884,
          0.0
        ],
        "relative_unit": "%",
        "absolute_max_diff": [
          -3.122092,
          2.159639,
          -0.37410799999999,
          -4.329858,
          -1.728906,
          -0.013072999999991,
          -0.19721699999999,
          -0.13274799999999,
          -0.062141999999994,
          0.452505,
          0.365329,
          0.13136300000001,
          0.200793,
          0.064546000000007,
          0.012014000000008,
          0.0
        ],
        "relative_max_diff": [
          -2.7023997987992,
          1.8693260797821,
          -0.3238179348748,
          -3.7478099261742,
          -1.4964950509283,
          -0.011315641105284,
          -0.17070578993821,
          -0.11490313818138,
          -0.053788462446643,
          0.39167629299701,
          0.31621906596459,
          0.1137043190174,
          0.1738010804295,
          0.055869300908914,
          0.010398998870884,
          0.0
        ]
      }
    },
    "convergence_pressure": {
      "output_parameters": {
        "ecutrho": [
          240.0,
          280.0,
          320.0,
          360.0,
          400.0,
          440.0,
          480.0,
          520.0,
          560.0,
          600.0,
          640.0,
          720.0,
          800.0,
          960.0,
          1200.0,
          1600.0
        ],
        "ecutwfc": [
          30.0,
          35.0,
          40.0,
          45.0,
          50.0,
          55.0,
          60.0,
          65.0,
          70.0,
          75.0,
          80.0,
          90.0,
          100.0,
          120.0,
          150.0,
          200.0
        ],
        "pressure": [
          -29.789803174144,
          -18.198807547802,
          -18.986996427234,
          -19.680449651878,
          -19.0827618174,
          -18.332378936851,
          -18.077887193399,
          -18.128344226928,
          -18.245145639818,
          -18.257061149194,
          -18.198660442748,
          -18.103630577852,
          -18.122754234875,
          -18.115546087228,
          -18.118782398416,
          -18.108926359797
        ],
        "absolute_diff": [
          11.680876814347,
          0.089881188005002,
          0.878070067437,
          1.571523292081,
          0.973835457603,
          0.223452577054,
          0.031039166397999,
          0.019417867131001,
          0.136219280021,
          0.148134789397,
          0.089734082951001,
          0.0052957819449979,
          0.013827875078,
          0.0066197274310014,
          0.0098560386189988,
          0.0
        ],
        "absolute_unit": "GPascal",
        "relative_diff": [
          3.8192403639876,
          0.03284813254928,
          0.31826791853581,
          0.56555635581852,
          0.35262881712863,
          0.081548776112709,
          0.011350657301105,
          0.0071017546412133,
          0.049758668631678,
          0.054104429671676,
          0.032794422056,
          0.0019371304454356,
          0.0050576080335287,
          0.0024213792688348,
          0.0036050417262406,
          3.3840251356655e-14
        ],
        "relative_unit": "%"
      }
    },
    "delta_factor": {
      "output_birch_murnaghan_fit": {
        "energy0": -833.1937211,
        "volume0": 11.3821134,
        "residuals0": 0,
        "bulk_deriv0": 5.2384075,
        "volume0_unit": "A^3/atom",
        "bulk_modulus0": 193.3980547,
        "bulk_modulus0_unit": "GPa"
      },
      "output_delta_factor": {
        "delta": 1.522989889333,
        "delta1": 2.0564984660229,
        "delta_unit": "meV/atom",
        "delta_relative": 13.432863884336,
        "delta_relative_unit": "%",
        "birch_murnaghan_results": [
          11.3821134,
          193.3980547,
          5.2384075
        ],
        "reference_wien2k_V0_B0_B1": [
          11.3436,
          197.652,
          5.8
        ]
      },
      "output_volume_energy": {
        "volumes": {
          "0": 10.692323777927,
          "1": 10.919820028664,
          "2": 11.147316279711,
          "3": 11.37481252979,
          "4": 11.602308780805,
          "5": 11.829805030753,
          "6": 12.057301282059
        },
        "energies": {
          "0": -833.1649819493,
          "1": -833.18138163785,
          "2": -833.1906660939,
          "3": -833.1937034285,
          "4": -833.1912530434,
          "5": -833.1839248818,
          "6": -833.17227092655
        },
        "energy_unit": "eV/atom",
        "volume_unit": "A^3/atom"
      }
    },
    "pseudo_info": {
      "element": "Fe",
      "pp_type": "USPP",
      "z_valence": 8
    }
  },
  "fe/psl/z=16/paw/v0.2.1": {
    "convergence_cohesive_energy": {
      "output_parameters": {
        "ecutrho": [
          440.0,
          480.0,
          520.0,
          560.0,
          640.0,
          720.0,
          800.0,
          960.0,
          1200.0,
          1600.0
        ],
        "ecutwfc": [
          55.0,
          60.0,
          65.0,
          70.0,
          80.0,
          90.0,
          100.0,
          120.0,
          150.0,
          200.0
        ],
        "absolute_diff": [
          0.049257638122899,
          0.0539458874009,
          0.0389801707215,
          0.018317206674499,
          0.0042121859904993,
          0.001578396208,
          -3.5374836500068e-05,
          -0.0016875139591006,
          0.00024068464330007,
          0.0
        ],
        "absolute_unit": "eV/atom",
        "relative_diff": [
          0.63783619833185,
          0.69854424707855,
          0.50475347277703,
          0.23718915308467,
          0.054543514492989,
          0.020438621808465,
          0.00045806807004262,
          0.021851585445878,
          0.0031166207664351,
          0.0
        ],
        "relative_unit": "%",
        "cohesive_energy_per_atom": [
          -7.6733580195842,
          -7.6686697703062,
          -7.6836354869856,
          -7.7042984510326,
          -7.7184034717166,
          -7.7210372614991,
          -7.7226510325436,
          -7.7243031716662,
          -7.7223749730638,
          -7.7226156577071
        ]
      }
    },
    "convergence_phonon_frequencies": {
      "output_parameters": {
        "ecutrho": [
          240.0,
          280.0,
          320.0,
          360.0,
          400.0,
          440.0,
          480.0,
          520.0,
          560.0,
          600.0,
          640.0,
          720.0,
          800.0,
          960.0,
          1200.0,
          1600.0
        ],
        "ecutwfc": [
          30.0,
          35.0,
          40.0,
          45.0,
          50.0,
          55.0,
          60.0,
          65.0,
          70.0,
          75.0,
          80.0,
          90.0,
          100.0,
          120.0,
          150.0,
          200.0
        ],
        "absolute_diff": [
          -139.412968,
          246.659665,
          8.739049,
          -36.215426,
          -30.108829,
          6.608992,
          20.631811,
          4.256545,
          -10.802303,
          -11.650109,
          -2.74226,
          4.796455,
          -1.77649,
          1.220477,
          -0.60889399999999,
          0.0
        ],
        "absolute_unit": "cm-1",
        "relative_diff": [
          74.486243528948,
          131.78653420504,
          4.6691419124325,
          19.349355223114,
          16.086692661657,
          3.5310846232961,
          11.023265056585,
          2.2742077154683,
          5.7715073674602,
          6.2244773105526,
          1.4651481071667,
          2.5626734752942,
          0.94915178024717,
          0.6520824306924,
          0.32532286929947,
          0.0
        ],
        "relative_unit": "%",
        "absolute_max_diff": [
          -139.412968,
          246.659665,
          8.739049,
          -36.215426,
          -30.108829,
          6.608992,
          20.631811,
          4.256545,
          -10.802303,
          -11.650109,
          -2.74226,
          4.796455,
          -1.77649,
          1.220477,
          -0.60889399999999,
          0.0
        ],
        "relative_max_diff": [
          74.486243528948,
          -131.78653420504,
          -4.6691419124325,
          19.349355223114,
          16.086692661657,
          -3.5310846232961,
          -11.023265056585,
          -2.2742077154683,
          5.7715073674602,
          6.2244773105526,
          1.4651481071667,
          -2.5626734752942,
          0.94915178024717,
          -0.6520824306924,
          0.32532286929947,
          0.0
        ]
      }
    },
    "convergence_pressure": {
      "output_parameters": {
        "ecutrho": [
          240.0,
          280.0,
          320.0,
          360.0,
          400.0,
          440.0,
          480.0,
          520.0,
          560.0,
          600.0,
          640.0,
          720.0,
          800.0,
          960.0,
          1200.0,
          1600.0
        ],
        "ecutwfc": [
          30.0,
          35.0,
          40.0,
          45.0,
          50.0,
          55.0,
          60.0,
          65.0,
          70.0,
          75.0,
          80.0,
          90.0,
          100.0,
          120.0,
          150.0,
          200.0
        ],
        "pressure": [
          -124.41968942828,
          -110.98826247111,
          -85.947157545742,
          -50.112807701975,
          -26.246777948106,
          -18.859897660562,
          -18.55671414423,
          -19.916847473686,
          -20.515417938487,
          -20.18531419727,
          -19.309597810697,
          -17.749990027992,
          -17.503883272619,
          -17.852816460751,
          -17.528155606532,
          -17.540512431069
        ],
        "absolute_diff": [
          106.87917699721,
          93.447750040041,
          68.406645114673,
          32.572295270906,
          8.706265517037,
          1.319385229493,
          1.016201713161,
          2.376335042617,
          2.974905507418,
          2.644801766201,
          1.769085379628,
          0.209477596923,
          0.036629158450001,
          0.312304029682,
          0.012356824537001,
          0.0
        ],
        "absolute_unit": "GPascal",
        "relative_diff": [
          20.456405541437,
          18.904985688923,
          15.546708315979,
          9.1300256602773,
          2.9459006772685,
          0.47961108514577,
          0.37055766461788,
          0.85456191797533,
          1.0633926856293,
          0.94853376592083,
          0.64012441094333,
          0.077030349233611,
          0.01349396281398,
          0.1147186526268,
          0.0045533426318912,
          1.3499185742375e-13
        ],
        "relative_unit": "%"
      }
    },
    "delta_factor": {
      "output_birch_murnaghan_fit": {
        "energy0": -4479.9800124,
        "volume0": 11.3740005,
        "residuals0": 0,
        "bulk_deriv0": 5.2065703,
        "volume0_unit": "A^3/atom",
        "bulk_modulus0": 195.5024063,
        "bulk_modulus0_unit": "GPa"
      },
      "output_delta_factor": {
        "delta": 1.1894685115485,
        "delta1": 1.598117069444,
        "delta_unit": "meV/atom",
        "delta_relative": 10.44283519278,
        "delta_relative_unit": "%",
        "birch_murnaghan_results": [
          11.3740005,
          195.5024063,
          5.2065703
        ],
        "reference_wien2k_V0_B0_B1": [
          11.3436,
          197.652,
          5.8
        ]
      },
      "output_volume_energy": {
        "volumes": {
          "0": 10.692323777927,
          "1": 10.919820028664,
          "2": 11.147316279711,
          "3": 11.37481252979,
          "4": 11.602308780805,
          "5": 11.829805030753,
          "6": 12.057301282059
        },
        "energies": {
          "0": -4479.9516937436,
          "1": -4479.9679517288,
          "2": -4479.9771478839,
          "3": -4479.9800290932,
          "4": -4479.9773233973,
          "5": -4479.9697241423,
          "6": -4479.9578218832
        },
        "energy_unit": "eV/atom",
        "volume_unit": "A^3/atom"
      }
    },
    "pseudo_info": {
      "element": "Fe",
      "pp_type": "PAW",
      "z_valence": 16
    }
  },
  "fe/gbrv/z=16/us/v1.5": {
    "convergence_phonon_frequencies": {
      "output_parameters": {
        "ecutrho": [
          240.0,
          280.0,
          320.0,
          360.0,
          400.0,
          440.0,
          480.0,
          520.0,
          560.0,
          600.0,
          640.0,
          720.0,
          800.0,
          960.0,
          1200.0,
          1600.0
        ],
        "ecutwfc": [
          30.0,
          35.0,
          40.0,
          45.0,
          50.0,
          55.0,
          60.0,
          65.0,
          70.0,
          75.0,
          80.0,
          90.0,
          100.0,
          120.0,
          150.0,
          200.0
        ],
        "absolute_diff": [
          -22.324698,
          9.171181,
          0.515458,
          -6.731909,
          2.579062,
          5.306014,
          -1.306018,
          -7.631155,
          -1.607482,
          8.140463,
          11.553372,
          -1.520099,
          -6.88652,
          6.249768,
          -2.85083,
          0.0
        ],
        "absolute_unit": "cm-1",
        "relative_diff": [
          14.191041346789,
          5.8298037791995,
          0.32765889108705,
          4.2792426111127,
          1.639420854783,
          3.3728502871861,
          0.83019064525089,
          4.8508623108253,
          1.0218209234552,
          5.1746118588035,
          7.3440805222465,
          0.96627456103608,
          4.3775234968684,
          3.9727621890267,
          1.8121744089289,
          0.0
        ],
        "relative_unit": "%",
        "absolute_max_diff": [
          -22.324698,
          9.171181,
          0.515458,
          -6.731909,
          2.579062,
          5.306014,
          -1.306018,
          -7.631155,
          -1.607482,
          8.140463,
          11.553372,
          -1.520099,
          -6.88652,
          6.249768,
          -2.85083,
          0.0
        ],
        "relative_max_diff": [
          14.191041346789,
          -5.8298037791995,
          -0.32765889108705,
          4.2792426111127,
          -1.639420854783,
          -3.3728502871861,
          0.83019064525089,
          4.8508623108253,
          1.0218209234552,
          -5.1746118588035,
          -7.3440805222465,
          0.96627456103608,
          4.3775234968684,
          -3.9727621890267,
          1.8121744089289,
          0.0
        ]
      }
    },
    "convergence_pressure": {
      "output_parameters": {
        "ecutrho": [
          240.0,
          280.0,
          320.0,
          360.0,
          400.0,
          440.0,
          480.0,
          520.0,
          560.0,
          600.0,
          640.0,
          720.0,
          800.0,
          960.0,
          1200.0,
          1600.0
        ],
        "ecutwfc": [
          30.0,
          35.0,
          40.0,
          45.0,
          50.0,
          55.0,
          60.0,
          65.0,
          70.0,
          75.0,
          80.0,
          90.0,
          100.0,
          120.0,
          150.0,
          200.0
        ],
        "pressure": [
          -53.857955272234,
          -21.279334484006,
          -18.372538616598,
          -18.86239844648,
          -18.667778460014,
          -18.407108304293,
          -18.469775057305,
          -18.670132140878,
          -18.72985679281,
          -18.577897272008,
          -18.399753051592,
          -18.457859547929,
          -18.665718989258,
          -18.446238248662,
          -18.646301122127,
          -18.595402773437
        ],
        "absolute_diff": [
          35.262552498797,
          2.683931710569,
          0.222864156839,
          0.266995673043,
          0.072375686576997,
          0.188294469144,
          0.125627716132,
          0.074729367440998,
          0.134454019373,
          0.017505501429003,
          0.195649721845,
          0.137543225508,
          0.070316215820998,
          0.149164524775,
          0.050898348689998,
          0.0
        ],
        "absolute_unit": "GPascal",
        "relative_diff": [
          9.7008065725411,
          0.96070326296007,
          0.081804706446251,
          0.097958576123925,
          0.026608065027653,
          0.069140459401912,
          0.046159844612667,
          0.027472691808198,
          0.049398370138507,
          0.0064393858820573,
          0.071835744671304,
          0.050531713059693,
          0.025851481689662,
          0.054794586491429,
          0.018716379488267,
          0.0
        ],
        "relative_unit": "%"
      }
    },
    "delta_factor": {
      "output_birch_murnaghan_fit": {
        "energy0": -3406.1648535,
        "volume0": 11.3946973,
        "residuals0": 0,
        "bulk_deriv0": 5.4274234,
        "volume0_unit": "A^3/atom",
        "bulk_modulus0": 188.9470808,
        "bulk_modulus0_unit": "GPa"
      },
      "output_delta_factor": {
        "delta": 2.055079066434,
        "delta1": 2.8053756549987,
        "delta_unit": "meV/atom",
        "delta_relative": 18.303477114542,
        "delta_relative_unit": "%",
        "birch_murnaghan_results": [
          11.3946973,
          188.9470808,
          5.4274234
        ],
        "reference_wien2k_V0_B0_B1": [
          11.3436,
          197.652,
          5.8
        ]
      },
      "output_volume_energy": {
        "volumes": {
          "0": 10.692323777927,
          "1": 10.919820028664,
          "2": 11.147316279711,
          "3": 11.37481252979,
          "4": 11.602308780805,
          "5": 11.829805030753,
          "6": 12.057301282059
        },
        "energies": {
          "0": -3406.1356017079,
          "1": -3406.1520618057,
          "2": -3406.1615222514,
          "3": -3406.1648476865,
          "4": -3406.1627346546,
          "5": -3406.1557692887,
          "6": -3406.1447407871
        },
        "energy_unit": "eV/atom",
        "volume_unit": "A^3/atom"
      }
    },
    "pseudo_info": {
      "element": "Fe",
      "pp_type": "US",
      "z_valence": 16
    }
  },
  "fe/psl(low)/z=8/paw/v1.0.0": {
    "convergence_cohesive_energy": {
      "output_parameters": {
        "ecutrho": [
          240.0,
          320.0,
          360.0,
          520.0,
          560.0,
          600.0,
          720.0,
          800.0,
          1600.0
        ],
        "ecutwfc": [
          30.0,
          40.0,
          45.0,
          65.0,
          70.0,
          75.0,
          90.0,
          100.0,
          200.0
        ],
        "absolute_diff": [
          -0.0030563825967,
          -0.0041536816143006,
          -0.0015068304035006,
          -0.00020789491650053,
          -0.00023782744900025,
          -0.00024299763820057,
          -5.6735755200599e-05,
          -7.4014955299795e-05,
          0.0
        ],
        "absolute_unit": "eV/atom",
        "relative_diff": [
          0.039464583892034,
          0.053633114095517,
          0.019456476075418,
          0.0026843780558824,
          0.0030708725154477,
          0.0031376309656673,
          0.00073258268556084,
          0.00095569494992141,
          0.0
        ],
        "relative_unit": "%",
        "cohesive_energy_per_atom": [
          -7.7476777501033,
          -7.7487750491209,
          -7.7461281979101,
          -7.7448292624231,
          -7.7448591949556,
          -7.7448643651448,
          -7.7446781032618,
          -7.7446953824619,
          -7.7446213675066
        ]
      }
    },
    "convergence_phonon_frequencies": {
      "output_parameters": {
        "ecutrho": [
          240.0,
          280.0,
          320.0,
          360.0,
          400.0,
          440.0,
          480.0,
          520.0,
          560.0,
          600.0,
          640.0,
          720.0,
          800.0,
          960.0,
          1200.0,
          1600.0
        ],
        "ecutwfc": [
          30.0,
          35.0,
          40.0,
          45.0,
          50.0,
          55.0,
          60.0,
          65.0,
          70.0,
          75.0,
          80.0,
          90.0,
          100.0,
          120.0,
          150.0,
          200.0
        ],
        "absolute_diff": [
          -2.66873,
          2.222522,
          -0.33834999999999,
          -4.198306,
          -1.662815,
          0.079917000000009,
          -0.170457,
          -0.16280599999999,
          0.021798000000004,
          0.475296,
          0.39931800000001,
          0.16046600000001,
          0.200613,
          0.043360000000007,
          0.019065000000012,
          0.0
        ],
        "absolute_unit": "cm-1",
        "relative_diff": [
          2.3355360100782,
          1.9450375887374,
          0.29610661588469,
          3.6741426987096,
          1.455210647236,
          0.069939271232924,
          0.14917524877747,
          0.14247948486987,
          0.01907649479254,
          0.41595475130348,
          0.34946269141968,
          0.14043163654369,
          0.17556623771975,
          0.037946454454743,
          0.016684712965406,
          0.0
        ],
        "relative_unit": "%",
        "absolute_max_diff": [
          -2.66873,
          2.222522,
          -0.33834999999999,
          -4.198306,
          -1.662815,
          0.079917000000009,
          -0.170457,
          -0.16280599999999,
          0.021798000000004,
          0.475296,
          0.39931800000001,
          0.16046600000001,
          0.200613,
          0.043360000000007,
          0.019065000000012,
          0.0
        ],
        "relative_max_diff": [
          -2.3355360100782,
          1.9450375887374,
          -0.29610661588469,
          -3.6741426987096,
          -1.455210647236,
          0.069939271232924,
          -0.14917524877747,
          -0.14247948486987,
          0.01907649479254,
          0.41595475130348,
          0.34946269141968,
          0.14043163654369,
          0.17556623771975,
          0.037946454454743,
          0.016684712965406,
          0.0
        ]
      }
    },
    "convergence_pressure": {
      "output_parameters": {
        "ecutrho": [
          240.0,
          280.0,
          320.0,
          360.0,
          400.0,
          440.0,
          480.0,
          520.0,
          560.0,
          600.0,
          640.0,
          720.0,
          800.0,
          960.0,
          1200.0,
          1600.0
        ],
        "ecutwfc": [
          30.0,
          35.0,
          40.0,
          45.0,
          50.0,
          55.0,
          60.0,
          65.0,
          70.0,
          75.0,
          80.0,
          90.0,
          100.0,
          120.0,
          150.0,
          200.0
        ],
        "pressure": [
          -29.481323875867,
          -18.04934881292,
          -18.858132399914,
          -19.531579337211,
          -18.936833603814,
          -18.181596256482,
          -17.934165555623,
          -17.991830736798,
          -18.097599270638,
          -18.116428717552,
          -18.056115645404,
          -17.960497360292,
          -17.983004433557,
          -17.977414441505,
          -17.977561546559,
          -17.969470768587
        ],
        "absolute_diff": [
          11.51185310728,
          0.079878044333,
          0.888661631327,
          1.562108568624,
          0.967362835227,
          0.212125487895,
          0.035305212964001,
          0.022359968210999,
          0.128128502051,
          0.146957948965,
          0.086644876816997,
          0.0089734082950024,
          0.013533664969998,
          0.0079436729179996,
          0.0080907779719972,
          0.0
        ],
        "absolute_unit": "GPascal",
        "relative_diff": [
          3.7836388670032,
          0.02930078349489,
          0.32323715156398,
          0.56426215042295,
          0.35157671895075,
          0.077703678387634,
          0.012956694555696,
          0.0082070243231405,
          0.046976143826972,
          0.053868987980937,
          0.031780725450936,
          0.0032940724867081,
          0.0049678708789426,
          0.0029160957746528,
          0.0029700929496377,
          1.0146556913055e-13
        ],
        "relative_unit": "%"
      }
    },
    "delta_factor": {
      "output_birch_murnaghan_fit": {
        "energy0": -1928.7901041,
        "volume0": 11.3558028,
        "residuals0": 0,
        "bulk_deriv0": 5.2633738,
        "volume0_unit": "A^3/atom",
        "bulk_modulus0": 195.8943144,
        "bulk_modulus0_unit": "GPa"
      },
      "output_delta_factor": {
        "delta": 0.42480738876055,
        "delta1": 0.57064107210568,
        "delta_unit": "meV/atom",
        "delta_relative": 3.7299307649341,
        "delta_relative_unit": "%",
        "birch_murnaghan_results": [
          11.3558028,
          195.8943144,
          5.2633738
        ],
        "reference_wien2k_V0_B0_B1": [
          11.3436,
          197.652,
          5.8
        ]
      },
      "output_volume_energy": {
        "volumes": {
          "0": 10.692323777927,
          "1": 10.919820028664,
          "2": 11.147316279711,
          "3": 11.37481252979,
          "4": 11.602308780805,
          "5": 11.829805030753,
          "6": 12.057301282059
        },
        "energies": {
          "0": -1928.763238468,
          "1": -1928.7789791648,
          "2": -1928.7876822497,
          "3": -1928.7900978721,
          "4": -1928.7869693794,
          "5": -1928.778988961,
          "6": -1928.76673343
        },
        "energy_unit": "eV/atom",
        "volume_unit": "A^3/atom"
      }
    },
    "pseudo_info": {
      "element": "Fe",
      "pp_type": "PAW",
      "z_valence": 8
    }
  },
  "fe/psl/z=16/us/v0.2.1": {
    "convergence_cohesive_energy": {
      "output_parameters": {
        "ecutrho": [
          440.0,
          480.0,
          560.0,
          600.0,
          720.0,
          800.0,
          960.0,
          1200.0,
          1600.0
        ],
        "ecutwfc": [
          55.0,
          60.0,
          70.0,
          75.0,
          90.0,
          100.0,
          120.0,
          150.0,
          200.0
        ],
        "absolute_diff": [
          0.0494319270484,
          0.0541189517276,
          0.0184210180724,
          0.0121195419347,
          0.0015945870346004,
          -2.1088866099639e-05,
          -0.0016824798599,
          0.00024190914339961,
          0.0
        ],
        "absolute_unit": "eV/atom",
        "relative_diff": [
          0.64056233243953,
          0.70129901903017,
          0.23870828039566,
          0.15705076684931,
          0.020663414338699,
          0.00027327951920756,
          0.021802371214152,
          0.0031347733011254,
          0.0
        ],
        "relative_unit": "%",
        "cohesive_energy_per_atom": [
          -7.6675262119265,
          -7.6628391872473,
          -7.6985371209025,
          -7.7048385970402,
          -7.7153635519403,
          -7.716979227841,
          -7.7186406188348,
          -7.7167162298315,
          -7.7169581389749
        ]
      }
    },
    "convergence_phonon_frequencies": {
      "output_parameters": {
        "ecutrho": [
          240.0,
          280.0,
          320.0,
          360.0,
          400.0,
          440.0,
          480.0,
          520.0,
          560.0,
          600.0,
          640.0,
          720.0,
          800.0,
          960.0,
          1200.0,
          1600.0
        ],
        "ecutwfc": [
          30.0,
          35.0,
          40.0,
          45.0,
          50.0,
          55.0,
          60.0,
          65.0,
          70.0,
          75.0,
          80.0,
          90.0,
          100.0,
          120.0,
          150.0,
          200.0
        ],
        "absolute_diff": [
          -138.711917,
          247.719765,
          9.44023,
          -35.983311,
          -29.901623,
          6.625373,
          20.513631,
          4.245652,
          -10.78065,
          -11.551133,
          -2.73816,
          4.729316,
          -1.767971,
          1.232418,
          -0.44972299999998,
          0.0
        ],
        "absolute_unit": "cm-1",
        "relative_diff": [
          73.683743713516,
          131.58869166975,
          5.0146483659125,
          19.114327903692,
          15.883736404207,
          3.5193968672385,
          10.896836853878,
          2.2552895283307,
          5.7266792128979,
          6.135959634764,
          1.45451006698,
          2.5122117523921,
          0.93914585620591,
          0.65466020529387,
          0.23889277136925,
          0.0
        ],
        "relative_unit": "%",
        "absolute_max_diff": [
          -138.711917,
          247.719765,
          9.44023,
          -35.983311,
          -29.901623,
          6.625373,
          20.513631,
          4.245652,
          -10.78065,
          -11.551133,
          -2.73816,
          4.729316,
          -1.767971,
          1.232418,
          -0.44972299999998,
          0.0
        ],
        "relative_max_diff": [
          73.683743713516,
          -131.58869166975,
          -5.0146483659125,
          19.114327903692,
          15.883736404207,
          -3.5193968672385,
          -10.896836853878,
          -2.2552895283307,
          5.7266792128979,
          6.135959634764,
          1.45451006698,
          -2.5122117523921,
          0.93914585620591,
          -0.65466020529387,
          0.23889277136925,
          0.0
        ]
      }
    },
    "convergence_pressure": {
      "output_parameters": {
        "ecutrho": [
          240.0,
          280.0,
          320.0,
          360.0,
          400.0,
          440.0,
          480.0,
          520.0,
          560.0,
          600.0,
          640.0,
          720.0,
          800.0,
          960.0,
          1200.0,
          1600.0
        ],
        "ecutwfc": [
          30.0,
          35.0,
          40.0,
          45.0,
          50.0,
          55.0,
          60.0,
          65.0,
          70.0,
          75.0,
          80.0,
          90.0,
          100.0,
          120.0,
          150.0,
          200.0
        ],
        "pressure": [
          -122.91186262459,
          -110.17035837077,
          -85.70472841672,
          -50.103981398734,
          -26.261341348454,
          -18.874755271018,
          -18.578779902333,
          -19.936265340816,
          -20.546162894777,
          -20.201495753212,
          -19.33681224569,
          -17.781470509552,
          -17.530215077288,
          -17.876500374448,
          -17.557282407227,
          -17.565667395306
        ],
        "absolute_diff": [
          105.34619522928,
          92.604690975464,
          68.139061021414,
          32.538314003428,
          8.695673953148,
          1.309087875712,
          1.013112507027,
          2.37059794551,
          2.980495499471,
          2.635828357906,
          1.771144850384,
          0.215803114246,
          0.035452318018002,
          0.310832979142,
          0.0083849880790012,
          0.0
        ],
        "absolute_unit": "GPascal",
        "relative_diff": [
          20.24078474977,
          18.760538141163,
          15.473669923984,
          9.1052904388129,
          2.9379933679723,
          0.47525289803475,
          0.36892932005552,
          0.8513330832367,
          1.0637967156791,
          0.94404718918502,
          0.63995244419295,
          0.079242513100994,
          0.013042768324329,
          0.1140234439548,
          0.0030856848942199,
          3.3751421512501e-14
        ],
        "relative_unit": "%"
      }
    },
    "delta_factor": {
      "output_birch_murnaghan_fit": {
        "energy0": -3460.946191,
        "volume0": 11.3802193,
        "residuals0": 0,
        "bulk_deriv0": 5.2839935,
        "volume0_unit": "A^3/atom",
        "bulk_modulus0": 194.6297727,
        "bulk_modulus0_unit": "GPa"
      },
      "output_delta_factor": {
        "delta": 1.4611283636637,
        "delta1": 1.9669356923734,
        "delta_unit": "meV/atom",
        "delta_relative": 12.846882348797,
        "delta_relative_unit": "%",
        "birch_murnaghan_results": [
          11.3802193,
          194.6297727,
          5.2839935
        ],
        "reference_wien2k_V0_B0_B1": [
          11.3436,
          197.652,
          5.8
        ]
      },
      "output_volume_energy": {
        "volumes": {
          "0": 10.692323777927,
          "1": 10.919820028664,
          "2": 11.147316279711,
          "3": 11.37481252979,
          "4": 11.602308780805,
          "5": 11.829805030753,
          "6": 12.057301282059
        },
        "energies": {
          "0": -3460.9174177796,
          "1": -3460.9338361079,
          "2": -3460.9431772997,
          "3": -3460.9462023212,
          "4": -3460.9436564242,
          "5": -3460.9362345874,
          "6": -3460.9245177738
        },
        "energy_unit": "eV/atom",
        "volume_unit": "A^3/atom"
      }
    },
    "pseudo_info": {
      "element": "Fe",
      "pp_type": "USPP",
      "z_valence": 16
    }
  },
  "fe/psl/z=16/us/v1.0.0": {
    "convergence_cohesive_energy": {
      "output_parameters": {
        "ecutrho": [
          240.0,
          280.0,
          360.0,
          440.0,
          480.0,
          520.0,
          560.0,
          640.0,
          720.0,
          960.0,
          1200.0,
          1600.0
        ],
        "ecutwfc": [
          30.0,
          35.0,
          45.0,
          55.0,
          60.0,
          65.0,
          70.0,
          80.0,
          90.0,
          120.0,
          150.0,
          200.0
        ],
        "absolute_diff": [
          -0.0270893403417,
          -0.3898044284442,
          0.0178852260392,
          -0.00082164769489967,
          -0.00016925477439944,
          -0.0008987920186998,
          -0.00016966293789977,
          -0.0013937669704998,
          0.00051511151830042,
          -9.9865753799833e-05,
          -9.8369127499609e-05,
          0.0
        ],
        "absolute_unit": "eV/atom",
        "relative_diff": [
          0.35215392223465,
          5.0673496161054,
          0.23250298531864,
          0.010681192483989,
          0.0022002651932411,
          0.011684047328798,
          0.0022055712057073,
          0.018118584622271,
          0.0066963070812951,
          0.0012982271422607,
          0.0012787714148382,
          0.0
        ],
        "relative_unit": "%",
        "cohesive_energy_per_atom": [
          -7.7195609078312,
          -8.0822759959337,
          -7.6745863414503,
          -7.6932932151844,
          -7.6926408222639,
          -7.6933703595082,
          -7.6926412304274,
          -7.69386533446,
          -7.6919564559712,
          -7.6925714332433,
          -7.692569936617,
          -7.6924715674895
        ]
      }
    },
    "convergence_phonon_frequencies": {
      "output_parameters": {
        "ecutrho": [
          240.0,
          280.0,
          320.0,
          360.0,
          400.0,
          440.0,
          480.0,
          520.0,
          560.0,
          600.0,
          640.0,
          720.0,
          800.0,
          960.0,
          1200.0,
          1600.0
        ],
        "ecutwfc": [
          30.0,
          35.0,
          40.0,
          45.0,
          50.0,
          55.0,
          60.0,
          65.0,
          70.0,
          75.0,
          80.0,
          90.0,
          100.0,
          120.0,
          150.0,
          200.0
        ],
        "absolute_diff": [
          -540.837258,
          608.667005,
          408.8147,
          -73.813406,
          -1.131482,
          9.843849,
          2.256672,
          2.692614,
          2.767793,
          4.206947,
          3.383945,
          0.0069880000000069,
          1.253121,
          0.77527500000002,
          0.17872600000001,
          0.0
        ],
        "absolute_unit": "cm-1",
        "relative_diff": [
          274.26098007783,
          308.65774660136,
          207.31175345953,
          37.431106627722,
          0.57377955691879,
          4.991859629756,
          1.1443684126403,
          1.3654365406373,
          1.4035601460589,
          2.1333615432158,
          1.7160135669305,
          0.0035436458942807,
          0.63546323507193,
          0.39314540221607,
          0.090632749871299,
          0.0
        ],
        "relative_unit": "%",
        "absolute_max_diff": [
          -540.837258,
          608.667005,
          408.8147,
          -73.813406,
          -1.131482,
          9.843849,
          2.256672,
          2.692614,
          2.767793,
          4.206947,
          3.383945,
          0.0069880000000069,
          1.253121,
          0.77527500000002,
          0.17872600000001,
          0.0
        ],
        "relative_max_diff": [
          274.26098007783,
          -308.65774660136,
          -207.31175345953,
          37.431106627722,
          0.57377955691879,
          -4.991859629756,
          -1.1443684126403,
          -1.3654365406373,
          -1.4035601460589,
          -2.1333615432158,
          -1.7160135669305,
          -0.0035436458942807,
          -0.63546323507193,
          -0.39314540221607,
          -0.090632749871299,
          0.0
        ]
      }
    },
    "convergence_pressure": {
      "output_parameters": {
        "ecutrho": [
          240.0,
          280.0,
          320.0,
          360.0,
          400.0,
          440.0,
          480.0,
          520.0,
          560.0,
          600.0,
          640.0,
          720.0,
          800.0,
          960.0,
          1200.0,
          1600.0
        ],
        "ecutwfc": [
          30.0,
          35.0,
          40.0,
          45.0,
          50.0,
          55.0,
          60.0,
          65.0,
          70.0,
          75.0,
          80.0,
          90.0,
          100.0,
          120.0,
          150.0,
          200.0
        ],
        "pressure": [
          -1856.4578380418,
          -735.01128503424,
          -279.47018162453,
          -108.40671587814,
          -42.76579288407,
          -21.51632072603,
          -19.06775710189,
          -20.63486724235,
          -21.839069214547,
          -21.72609253306,
          -20.61324279941,
          -18.310018968641,
          -17.457986495765,
          -17.924603727112,
          -17.43400837196,
          -17.488290136893
        ],
        "absolute_diff": [
          1838.9695479049,
          717.52299489735,
          261.98189148764,
          90.918425741247,
          25.277502747177,
          4.028030589137,
          1.579466964997,
          3.146577105457,
          4.350779077654,
          4.237802396167,
          3.124952662517,
          0.821728831748,
          0.030303641128,
          0.436313590219,
          0.054281764932998,
          0.0
        ],
        "absolute_unit": "GPascal",
        "relative_diff": [
          57.529339974828,
          45.735053481836,
          32.024846795232,
          18.643098572572,
          7.4926107322169,
          1.4318303455712,
          0.57551323049556,
          1.1283817460515,
          1.5416330599461,
          1.5032756550079,
          1.1208706337636,
          0.30177860646963,
          0.011221975015772,
          0.16088396230194,
          0.0200963970877,
          6.7498671055336e-14
        ],
        "relative_unit": "%"
      }
    },
    "delta_factor": {
      "output_birch_murnaghan_fit": {
        "energy0": -3371.907525,
        "volume0": 11.4890618,
        "residuals0": 0,
        "bulk_deriv0": 8.0200162,
        "volume0_unit": "A^3/atom",
        "bulk_modulus0": 171.0937155,
        "bulk_modulus0_unit": "GPa"
      },
      "output_delta_factor": {
        "delta": 6.1025384782909,
        "delta1": 8.6977765394221,
        "delta_unit": "meV/atom",
        "delta_relative": 55.370923898856,
        "delta_relative_unit": "%",
        "birch_murnaghan_results": [
          11.4890618,
          171.0937155,
          8.0200162
        ],
        "reference_wien2k_V0_B0_B1": [
          11.3436,
          197.652,
          5.8
        ]
      },
      "output_volume_energy": {
        "volumes": {
          "0": 10.692323777927,
          "1": 10.919820028664,
          "2": 11.147316279711,
          "3": 11.37481252979,
          "4": 11.602308780805,
          "5": 11.829805030753,
          "6": 12.057301282059
        },
        "energies": {
          "0": -3371.8710735861,
          "1": -3371.8898342704,
          "2": -3371.901560744,
          "3": -3371.9070830901,
          "4": -3371.9070775118,
          "5": -3371.9022487838,
          "6": -3371.8946985772
        },
        "energy_unit": "eV/atom",
        "volume_unit": "A^3/atom"
      }
    },
    "pseudo_info": {
      "element": "Fe",
      "pp_type": "USPP",
      "z_valence": 16
    }
  },
  "fe/sg15/z=16/nc/v1.0": {
    "convergence_phonon_frequencies": {
      "output_parameters": {
        "ecutrho": [
          120.0,
          140.0,
          160.0,
          180.0,
          200.0,
          220.0,
          240.0,
          260.0,
          280.0,
          300.0,
          320.0,
          360.0,
          400.0,
          480.0,
          600.0,
          800.0
        ],
        "ecutwfc": [
          30.0,
          35.0,
          40.0,
          45.0,
          50.0,
          55.0,
          60.0,
          65.0,
          70.0,
          75.0,
          80.0,
          90.0,
          100.0,
          120.0,
          150.0,
          200.0
        ],
        "absolute_diff": [
          -378.758082,
          490.58134,
          552.074451,
          -125.086115,
          -64.788343,
          38.04684,
          10.457285,
          0.68590399999999,
          0.66536100000002,
          0.89067,
          0.52000000000001,
          0.50752500000002,
          0.21732600000001,
          0.049373000000003,
          -0.0029480000000035,
          0.0
        ],
        "absolute_unit": "cm-1",
        "relative_diff": [
          199.01822712167,
          257.77569690453,
          290.08721846149,
          65.72643074277,
          34.042999409873,
          19.991691277975,
          5.4947746863023,
          0.36040788181956,
          0.34961357370034,
          0.46800206457497,
          0.27323371571849,
          0.26667873378852,
          0.11419382788892,
          0.025943015858019,
          0.0015490249883444,
          0.0
        ],
        "relative_unit": "%",
        "absolute_max_diff": [
          -378.758082,
          490.58134,
          552.074451,
          -125.086115,
          -64.788343,
          38.04684,
          10.457285,
          0.68590399999999,
          0.66536100000002,
          0.89067,
          0.52000000000001,
          0.50752500000002,
          0.21732600000001,
          0.049373000000003,
          -0.0029480000000035,
          0.0
        ],
        "relative_max_diff": [
          199.01822712167,
          -257.77569690453,
          -290.08721846149,
          65.72643074277,
          34.042999409873,
          -19.991691277975,
          -5.4947746863023,
          -0.36040788181956,
          -0.34961357370034,
          -0.46800206457497,
          -0.27323371571849,
          -0.26667873378852,
          -0.11419382788892,
          -0.025943015858019,
          0.0015490249883444,
          0.0
        ]
      }
    },
    "convergence_pressure": {
      "output_parameters": {
        "ecutrho": [
          120.0,
          140.0,
          160.0,
          180.0,
          200.0,
          220.0,
          240.0,
          260.0,
          280.0,
          300.0,
          320.0,
          360.0,
          400.0,
          480.0,
          600.0,
          800.0
        ],
        "ecutwfc": [
          30.0,
          35.0,
          40.0,
          45.0,
          50.0,
          55.0,
          60.0,
          65.0,
          70.0,
          75.0,
          80.0,
          90.0,
          100.0,
          120.0,
          150.0,
          200.0
        ],
        "pressure": [
          -1446.6830293029,
          -863.96651748802,
          -482.73332553999,
          -259.54892099922,
          -128.81916027881,
          -56.411993220105,
          -29.42468843007,
          -20.75858259278,
          -18.453593501363,
          -18.069649310374,
          -18.076121932751,
          -18.073032726617,
          -18.074062461995,
          -18.062441162727,
          -18.064059318321,
          -18.061411427349
        ],
        "absolute_diff": [
          1428.6216178756,
          845.90510606067,
          464.67191411264,
          241.48750957187,
          110.75774885146,
          38.350581792756,
          11.363277002721,
          2.697171165431,
          0.392182074014,
          0.0082378830250001,
          0.014710505402,
          0.011621299268,
          0.012651034645998,
          0.0010297353780011,
          0.0026478909719998,
          0.0
        ],
        "absolute_unit": "GPascal",
        "relative_diff": [
          54.434986397732,
          47.797370040781,
          39.743383045276,
          30.787623382398,
          20.798493743948,
          10.289814888144,
          3.7301995135268,
          0.96008342930507,
          0.14291302432316,
          0.0030139397905135,
          0.0053816717359187,
          0.0042516577595214,
          0.0046283371821677,
          0.00037677082380888,
          0.00096882289419205,
          0.0
        ],
        "relative_unit": "%"
      }
    },
    "delta_factor": {
      "output_birch_murnaghan_fit": {
        "energy0": -3220.604474,
        "volume0": 11.4484095,
        "residuals0": 0,
        "bulk_deriv0": 6.9000266,
        "volume0_unit": "A^3/atom",
        "bulk_modulus0": 180.3726232,
        "bulk_modulus0_unit": "GPa"
      },
      "output_delta_factor": {
        "delta": 4.4274382798546,
        "delta1": 6.1663909457771,
        "delta_unit": "meV/atom",
        "delta_relative": 39.765261365742,
        "delta_relative_unit": "%",
        "birch_murnaghan_results": [
          11.4484095,
          180.3726232,
          6.9000266
        ],
        "reference_wien2k_V0_B0_B1": [
          11.3436,
          197.652,
          5.8
        ]
      },
      "output_volume_energy": {
        "volumes": {
          "0": 10.692323777927,
          "1": 10.919820028664,
          "2": 11.147316279711,
          "3": 11.37481252979,
          "4": 11.602308780805,
          "5": 11.829805030753,
          "6": 12.057301282059
        },
        "energies": {
          "0": -3220.5708974976,
          "1": -3220.5888293231,
          "2": -3220.5996748282,
          "3": -3220.6043037566,
          "4": -3220.6034400673,
          "5": -3220.5977091458,
          "6": -3220.5886604084
        },
        "energy_unit": "eV/atom",
        "volume_unit": "A^3/atom"
      }
    },
    "pseudo_info": {
      "element": "Fe",
      "pp_type": "NC",
      "z_valence": 16
    }
  },
  "fe/psl/z=16/paw/v1.0.0": {
    "convergence_cohesive_energy": {
      "output_parameters": {
        "ecutrho": [
          240.0,
          280.0,
          400.0,
          440.0,
          480.0,
          560.0,
          640.0,
          800.0,
          960.0,
          1200.0,
          1600.0
        ],
        "ecutwfc": [
          30.0,
          35.0,
          50.0,
          55.0,
          60.0,
          70.0,
          80.0,
          100.0,
          120.0,
          150.0,
          200.0
        ],
        "absolute_diff": [
          -0.0700318966474,
          -0.3940232812911,
          0.015103950553501,
          -0.00088083233919978,
          -0.00020762276199981,
          -0.00022735108269956,
          -0.0014295499713999,
          -0.00090096885470015,
          -0.00010694063989991,
          -9.8233013900106e-05,
          0.0
        ],
        "absolute_unit": "eV/atom",
        "relative_diff": [
          0.90864755918389,
          5.1123603664399,
          0.19597024301043,
          0.011428594588746,
          0.0026938570130694,
          0.0029498273824123,
          0.018548078153358,
          0.011689861190621,
          0.001387529912432,
          0.0012745504917711,
          0.0
        ],
        "relative_unit": "%",
        "cohesive_energy_per_atom": [
          -7.7772992457503,
          -8.101290630394,
          -7.6921633985494,
          -7.7081481814421,
          -7.7074749718649,
          -7.7074947001856,
          -7.7086968990743,
          -7.7081683179576,
          -7.7073742897428,
          -7.7073655821168,
          -7.7072673491029
        ]
      }
    },
    "convergence_phonon_frequencies": {
      "output_parameters": {
        "ecutrho": [
          240.0,
          280.0,
          320.0,
          360.0,
          400.0,
          440.0,
          480.0,
          520.0,
          560.0,
          600.0,
          640.0,
          720.0,
          800.0,
          960.0,
          1200.0,
          1600.0
        ],
        "ecutwfc": [
          30.0,
          35.0,
          40.0,
          45.0,
          50.0,
          55.0,
          60.0,
          65.0,
          70.0,
          75.0,
          80.0,
          90.0,
          100.0,
          120.0,
          150.0,
          200.0
        ],
        "absolute_diff": [
          -472.872097,
          591.531816,
          399.071633,
          -76.062884,
          -1.598822,
          10.268835,
          2.010168,
          2.566333,
          2.190898,
          3.644778,
          2.742681,
          -0.256283,
          0.650463,
          -0.11420699999999,
          -0.011562999999995,
          0.0
        ],
        "absolute_unit": "cm-1",
        "relative_diff": [
          263.96850909341,
          330.20720093544,
          222.77132580416,
          42.460120218989,
          0.8925006620675,
          5.7323091852389,
          1.1221238329638,
          1.4325884317239,
          1.2230116395211,
          2.0346022121844,
          1.5310301011244,
          0.14306329733807,
          0.36310399666155,
          0.06375307764888,
          0.0064547430267299,
          0.0
        ],
        "relative_unit": "%",
        "absolute_max_diff": [
          -472.872097,
          591.531816,
          399.071633,
          -76.062884,
          -1.598822,
          10.268835,
          2.010168,
          2.566333,
          2.190898,
          3.644778,
          2.742681,
          -0.256283,
          0.650463,
          -0.11420699999999,
          -0.011562999999995,
          0.0
        ],
        "relative_max_diff": [
          263.96850909341,
          -330.20720093544,
          -222.77132580416,
          42.460120218989,
          0.8925006620675,
          -5.7323091852389,
          -1.1221238329638,
          -1.4325884317239,
          -1.2230116395211,
          -2.0346022121844,
          -1.5310301011244,
          0.14306329733807,
          -0.36310399666155,
          0.06375307764888,
          0.0064547430267299,
          0.0
        ]
      }
    },
    "convergence_pressure": {
      "output_parameters": {
        "ecutrho": [
          240.0,
          280.0,
          320.0,
          360.0,
          400.0,
          440.0,
          480.0,
          520.0,
          560.0,
          600.0,
          640.0,
          720.0,
          800.0,
          960.0,
          1200.0,
          1600.0
        ],
        "ecutwfc": [
          30.0,
          35.0,
          40.0,
          45.0,
          50.0,
          55.0,
          60.0,
          65.0,
          70.0,
          75.0,
          80.0,
          90.0,
          100.0,
          120.0,
          150.0,
          200.0
        ],
        "pressure": [
          -1832.3070129033,
          -730.9157332253,
          -278.69596772523,
          -108.24563584399,
          -42.804040198115,
          -21.628856092354,
          -19.185146934997,
          -20.744019192432,
          -21.990293210078,
          -21.867166279864,
          -20.75931811805,
          -18.393868849431,
          -17.581260531032,
          -18.076710352967,
          -17.541836376555,
          -17.576994484466
        ],
        "absolute_diff": [
          1814.7300184188,
          713.33873874083,
          261.11897324076,
          90.668641359524,
          25.227045713649,
          4.051861607888,
          1.608152450531,
          3.167024707966,
          4.413298725612,
          4.290171795398,
          3.182323633584,
          0.816874364965,
          0.004266046566002,
          0.499715868501,
          0.035158107910998,
          0.0
        ],
        "absolute_unit": "GPascal",
        "relative_diff": [
          57.506704656491,
          45.766559780024,
          32.051100823424,
          18.643477339477,
          7.4866273291813,
          1.4401501260746,
          0.58580169635093,
          1.1355839773223,
          1.563053103872,
          1.5212817414599,
          1.1408951403365,
          0.30000409031166,
          0.001580125879575,
          0.18413263228674,
          0.013018178004272,
          6.7527865140728e-14
        ],
        "relative_unit": "%"
      }
    },
    "delta_factor": {
      "output_birch_murnaghan_fit": {
        "energy0": -4479.965629,
        "volume0": 11.3785255,
        "residuals0": 0,
        "bulk_deriv0": 5.1629395,
        "volume0_unit": "A^3/atom",
        "bulk_modulus0": 194.1456374,
        "bulk_modulus0_unit": "GPa"
      },
      "output_delta_factor": {
        "delta": 1.3633197022292,
        "delta1": 1.8376728118595,
        "delta_unit": "meV/atom",
        "delta_relative": 12.007810127471,
        "delta_relative_unit": "%",
        "birch_murnaghan_results": [
          11.3785255,
          194.1456374,
          5.1629395
        ],
        "reference_wien2k_V0_B0_B1": [
          11.3436,
          197.652,
          5.8
        ]
      },
      "output_volume_energy": {
        "volumes": {
          "0": 10.692323777927,
          "1": 10.919820028664,
          "2": 11.147316279711,
          "3": 11.37481252979,
          "4": 11.602308780805,
          "5": 11.829805030753,
          "6": 12.057301282059
        },
        "energies": {
          "0": -4479.9371461978,
          "1": -4479.9534139792,
          "2": -4479.9626682986,
          "3": -4479.9656465845,
          "4": -4479.9630620473,
          "5": -4479.9556017744,
          "6": -4479.943856729
        },
        "energy_unit": "eV/atom",
        "volume_unit": "A^3/atom"
      }
    },
    "pseudo_info": {
      "element": "Fe",
      "pp_type": "PAW",
      "z_valence": 16
    }
  }
}