{
    "Ag": "FCC",
    "Al": "FCC",
    "Ar": "FCC",
    "As": "DC",
    "Au": "FCC",
    "B": "DC",
    "Ba": "FCC",
    "Be": "FCC",
    "Bi": "BCC",
    "Br": "FCC",
    "C": "DC",
    "Ca": "FCC",
    "Cd": "FCC",
    "Cl": "DC",
    "Co": "FCC",
    "Cr": "BCC",
    "Cs": "FCC",
    "Cu": "FCC",
    "F": "DC",
    "Fe": "FCC",
    "Ga": "FCC",
    "Ge": "DC",
    "H": "DC",
    "He": "FCC",
    "Hf": "FCC",
    "Hg": "FCC",
    "I": "BCC",
    "In": "FCC",
    "Ir": "FCC",
    "K": "FCC",
    "Kr": "FCC",
    "La": "FCC",
    "Li": "FCC",
    "Lu": "FCC",
    "Mg": "FCC",
    "Mn": "FCC",
    "Mo": "BCC",
    "N": "DC",
    "Na": "FCC",
    "Nb": "BCC",
    "Ne": "FCC",
    "Ni": "FCC",
    "O": "DC",
    "Os": "FCC",
    "P": "DC",
    "Pb": "BCC",
    "Pd": "FCC",
    "Po": "BCC",
    "Pt": "FCC",
    "Rb": "FCC",
    "Re": "FCC",
    "Rh": "FCC",
    "Rn": "BCC",
    "Ru": "FCC",
    "S": "DC",
    "Sb": "BCC",
    "Sc": "FCC",
    "Se": "DC",
    "Si": "DC",
    "Sn": "DC",
    "Sr": "FCC",
    "Ta": "BCC",
    "Tc": "FCC",
    "Te": "BCC",
    "Ti": "FCC",
    "Tl": "BCC",
    "V": "BCC",
    "W": "BCC",
    "Xe": "FCC",
    "Y": "FCC",
    "Zn": "FCC",
    "Zr": "FCC",
    "At": "BCC",
    "Ce": "FCC",
    "Dy": "FCC",
    "Er": "FCC",
    "Eu": "BCC",
    "Gd": "BCC",
    "Ho": "FCC",
    "Nd": "FCC",
    "Pm": "FCC",
    "Pr": "FCC",
    "Sm": "FCC",
    "Tb": "FCC",
    "Tm": "FCC",
    "Fr": "FCC",
    "Ra": "FCC",
    "Yb": "FCC",
    "Am": "DC",
    "Cm": "DC",
    "Np": "BCC",
    "Pa": "FCC",
    "Pu": "DC",
    "Th": "FCC",
    "U": "BCC",
    "Ac": "DC"
}